pidm/__init__.py
pidm/pidm.py
pidm-1.0.0.dist-info/LICENSE
pidm-1.0.0.dist-info/METADATA
pidm-1.0.0.dist-info/WHEEL
pidm-1.0.0.dist-info/top_level.txt
pidm-1.0.0.dist-info/RECORD
